mid.cpython-311-x86_64-linux-gnu.so
python_mid-1.0.0.dist-info/LICENSE
python_mid-1.0.0.dist-info/WHEEL
python_mid-1.0.0.dist-info/top_level.txt
python_mid-1.0.0.dist-info/RECORD
python_mid-1.0.0.dist-info/METADATA
